alibabacloud_waf_openapi20211001/__init__.py
alibabacloud_waf_openapi20211001/client.py
alibabacloud_waf_openapi20211001/models/__init__.py
alibabacloud_waf_openapi20211001/models/_add_address_request.py
alibabacloud_waf_openapi20211001/models/_add_address_response.py
alibabacloud_waf_openapi20211001/models/_add_address_response_body.py
alibabacloud_waf_openapi20211001/models/_change_resource_group_request.py
alibabacloud_waf_openapi20211001/models/_change_resource_group_response.py
alibabacloud_waf_openapi20211001/models/_change_resource_group_response_body.py
alibabacloud_waf_openapi20211001/models/_clear_address_request.py
alibabacloud_waf_openapi20211001/models/_clear_address_response.py
alibabacloud_waf_openapi20211001/models/_clear_address_response_body.py
alibabacloud_waf_openapi20211001/models/_clear_major_protection_black_ip_request.py
alibabacloud_waf_openapi20211001/models/_clear_major_protection_black_ip_response.py
alibabacloud_waf_openapi20211001/models/_clear_major_protection_black_ip_response_body.py
alibabacloud_waf_openapi20211001/models/_copy_defense_template_request.py
alibabacloud_waf_openapi20211001/models/_copy_defense_template_response.py
alibabacloud_waf_openapi20211001/models/_copy_defense_template_response_body.py
alibabacloud_waf_openapi20211001/models/_create_api_export_request.py
alibabacloud_waf_openapi20211001/models/_create_api_export_response.py
alibabacloud_waf_openapi20211001/models/_create_api_export_response_body.py
alibabacloud_waf_openapi20211001/models/_create_certs_request.py
alibabacloud_waf_openapi20211001/models/_create_certs_response.py
alibabacloud_waf_openapi20211001/models/_create_certs_response_body.py
alibabacloud_waf_openapi20211001/models/_create_cloud_resource_request.py
alibabacloud_waf_openapi20211001/models/_create_cloud_resource_response.py
alibabacloud_waf_openapi20211001/models/_create_cloud_resource_response_body.py
alibabacloud_waf_openapi20211001/models/_create_cloud_resource_shrink_request.py
alibabacloud_waf_openapi20211001-7.4.0.dist-info/LICENSE
alibabacloud_waf_openapi20211001-7.4.0.dist-info/METADATA
alibabacloud_waf_openapi20211001-7.4.0.dist-info/WHEEL
alibabacloud_waf_openapi20211001-7.4.0.dist-info/top_level.txt
alibabacloud_waf_openapi20211001-7.4.0.dist-info/RECORD
